setup.py
statistician.py
statistician.egg-info/PKG-INFO
statistician.egg-info/SOURCES.txt
statistician.egg-info/dependency_links.txt
statistician.egg-info/top_level.txt