Metadata-Version: 1.0
Name: statistician
Version: 0.0.1
Summary: simple statsd client
Home-page: UNKNOWN
Author: UNKNOWN
Author-email: UNKNOWN
License: UNKNOWN
Platform: UNKNOWN
